mySort/Sort.py
MyDataSort001-0.0.4.dist-info/LICENSE
MyDataSort001-0.0.4.dist-info/METADATA
MyDataSort001-0.0.4.dist-info/WHEEL
MyDataSort001-0.0.4.dist-info/top_level.txt
MyDataSort001-0.0.4.dist-info/RECORD
