Metadata-Version: 2.1
Name: MyDataSort001
Version: 0.0.4
Summary: This is pip, which is a collection of functions used for data structures.
Home-page: https://github.com/YGC20
Download-URL: https://github.com/YGC20
Author: YGC20
Classifier: Programming Language :: Python :: 3
Classifier: License :: OSI Approved :: MIT License
License-File: LICENSE
